crython/__init__.py
crython/compat.py
crython/expression.py
crython/field.py
crython/job.py
crython/log.py
crython/tab.py
crython-0.2.0.dist-info/LICENSE.md
crython-0.2.0.dist-info/METADATA
crython-0.2.0.dist-info/WHEEL
crython-0.2.0.dist-info/top_level.txt
crython-0.2.0.dist-info/RECORD
